{
  "name": "Hero",
  "data": {
    "title": "Sample Title",
    "text": "Sample Text",
    "image": {
      "recommendedSizes": {
        "width": "1900",
        "height": "610"
      }
    }
  },
  "form": {
    "schema": {
      "type": "object",

      "properties": {
        "title": {
          "type": "text",
          "title": "Title"
        },
        "text": {
          "type": "text",
          "title": "Text"
        },
        "image": {
          "type": "image"
        }
      }
    }
  }
}